yosun
